iceclassic/__init__.py
iceclassic/example.py
iceclassic-0.0.4.dist-info/METADATA
iceclassic-0.0.4.dist-info/WHEEL
iceclassic-0.0.4.dist-info/licenses/LICENSE.md
iceclassic-0.0.4.dist-info/RECORD
