Metadata-Version: 2.3
Name: iceclassic
Version: 0.0.4
Summary: A small example package for the iceclassic challenge during MUDE course
Project-URL: Homepage, https://github.com/iceclassic/iceclassic
Project-URL: Issues, https://github.com/iceclassic/iceclassic/issues
Author-email: Gabriel Follet <g.f.follet@tudelft.nl>
License: Creative Commons Attribution 4.0 
License-File: LICENSE.md
Classifier: Development Status :: 1 - Planning
Classifier: Intended Audience :: Education
Classifier: License :: Other/Proprietary License
Classifier: Operating System :: OS Independent
Classifier: Programming Language :: Python :: 3
Requires-Python: >=3.8
